{"metadata": {"dbt_schema_version": "https://schemas.getdbt.com/dbt/run-results/v4.json", "dbt_version": "1.5.1", "generated_at": "2023-06-19T17:29:39.631019Z", "invocation_id": "dca8eeef-3668-4f86-b6af-f8b3bbc5aa19", "env": {}}, "results": [{"status": "success", "timing": [{"name": "compile", "started_at": "2023-06-19T17:29:39.447201Z", "completed_at": "2023-06-19T17:29:39.447203Z"}, {"name": "execute", "started_at": "2023-06-19T17:29:39.448624Z", "completed_at": "2023-06-19T17:29:39.558240Z"}], "thread_id": "Thread-1", "execution_time": 0.11520004272460938, "adapter_response": {"_message": "CREATE 4", "code": "CREATE", "rows_affected": 4}, "message": "CREATE 4", "failures": null, "unique_id": "seed.omega.customer_raw"}, {"status": "success", "timing": [{"name": "compile", "started_at": "2023-06-19T17:29:39.448426Z", "completed_at": "2023-06-19T17:29:39.448427Z"}, {"name": "execute", "started_at": "2023-06-19T17:29:39.472465Z", "completed_at": "2023-06-19T17:29:39.559074Z"}], "thread_id": "Thread-4", "execution_time": 0.11437320709228516, "adapter_response": {"_message": "CREATE 16", "code": "CREATE", "rows_affected": 16}, "message": "CREATE 16", "failures": null, "unique_id": "seed.omega.sales_raw"}, {"status": "success", "timing": [{"name": "compile", "started_at": "2023-06-19T17:29:39.447570Z", "completed_at": "2023-06-19T17:29:39.447571Z"}, {"name": "execute", "started_at": "2023-06-19T17:29:39.459110Z", "completed_at": "2023-06-19T17:29:39.559612Z"}], "thread_id": "Thread-2", "execution_time": 0.11638402938842773, "adapter_response": {"_message": "CREATE 8", "code": "CREATE", "rows_affected": 8}, "message": "CREATE 8", "failures": null, "unique_id": "seed.omega.location_raw"}, {"status": "success", "timing": [{"name": "compile", "started_at": "2023-06-19T17:29:39.448076Z", "completed_at": "2023-06-19T17:29:39.448077Z"}, {"name": "execute", "started_at": "2023-06-19T17:29:39.471163Z", "completed_at": "2023-06-19T17:29:39.560450Z"}], "thread_id": "Thread-3", "execution_time": 0.11629104614257812, "adapter_response": {"_message": "CREATE 4", "code": "CREATE", "rows_affected": 4}, "message": "CREATE 4", "failures": null, "unique_id": "seed.omega.product_raw"}, {"status": "success", "timing": [{"name": "compile", "started_at": "2023-06-19T17:29:39.565643Z", "completed_at": "2023-06-19T17:29:39.565644Z"}, {"name": "execute", "started_at": "2023-06-19T17:29:39.566398Z", "completed_at": "2023-06-19T17:29:39.605030Z"}], "thread_id": "Thread-1", "execution_time": 0.04136395454406738, "adapter_response": {"_message": "CREATE 4", "code": "CREATE", "rows_affected": 4}, "message": "CREATE 4", "failures": null, "unique_id": "seed.omega.store_raw"}, {"status": "error", "timing": [], "thread_id": "Thread-4", "execution_time": 0.05418586730957031, "adapter_response": {}, "message": "Database Error in model stg_product (models/staging/stg_product.sql)\n  column \"productid\" does not exist\n  LINE 10:     ProductID AS product_id,\n               ^\n  HINT:  Perhaps you meant to reference the column \"product_raw.ProductID\".\n  compiled Code at target/run/omega/models/staging/stg_product.sql", "failures": null, "unique_id": "model.omega.stg_product"}, {"status": "skipped", "timing": [], "thread_id": "Thread-3", "execution_time": 0.0, "adapter_response": {}, "message": null, "failures": null, "unique_id": "model.omega.dim_product"}], "elapsed_time": 0.2754080295562744, "args": {"vars": {}, "static_parser": true, "use_colors": true, "project_dir": "/Users/jzehqz/code3/omega", "indirect_selection": "eager", "log_format_file": "debug", "send_anonymous_usage_stats": true, "use_colors_file": true, "warn_error_options": {"include": [], "exclude": []}, "cache_selected_only": false, "defer": false, "full_refresh": true, "version_check": true, "populate_cache": true, "partial_parse": true, "log_level": "info", "show": false, "macro_debugging": false, "printer_width": 80, "which": "build", "log_level_file": "debug", "log_path": "/Users/jzehqz/code3/omega/logs", "select": [], "enable_legacy_logger": false, "favor_state": false, "introspect": true, "log_format": "default", "exclude": [], "write_json": true, "quiet": false, "print": true, "strict_mode": false, "profiles_dir": "/Users/jzehqz/.dbt", "resource_types": []}}